{
      "startIndex": 1,
      "totalResults": 10,
      "Resources": [
        {
          "meta": {
            "location": "Users/00000000-0000-0000-0000-000000000001",
            "resourceType": "User"
          },
          "schemas": [
            "urn:ietf:params:scim:schemas:core:2.0:User",
            "urn:ietf:params:scim:schemas:ian:2.0:User",
            "urn:ietf:params:scim:schemas:extension:enterprise:2.0:User"
          ],
          "name": {
            "formatted": "Unknown",
            "givenName": "Unknown",
            "familyName": "Unknown"
          },
          "active": true,
          "id": "00000000-0000-0000-0000-000000000001",
          "userName": null,
          "urn:ietf:params:scim:schemas:ian:2.0:User": {
            "loadToDataVaultDate": "1900-01-01 00:00:00",
            "tenantKey": "709",
            "loadToDataMartDate": "1900-01-01 00:00:00",
            "EXTERNAL_USER_ID": "00000000-0000-0000-0000-000000000001"
          }
        },
        {
          "emails": [
            {
              "type": "work",
              "value": "test1@mail.com",
              "primary": true
            }
          ],
          "addresses": [
            {
              "country": "United States",
              "streetAddress": "3601 Antares Way",
              "formatted": "3601 Antares Way  Arlington Texas United States",
              "postalCode": "76016",
              "locality": "Arlington",
              "region": "Texas",
              "type": "home",
              "primary": true
            }
          ],
          "meta": {
            "location": "Users/048A0501-6188-4CDE-A301-2FA840E87CC7",
            "resourceType": "User"
          },
          "schemas": [
            "urn:ietf:params:scim:schemas:core:2.0:User",
            "urn:ietf:params:scim:schemas:ian:2.0:User",
            "urn:ietf:params:scim:schemas:extension:enterprise:2.0:User"
          ],
          "name": {
            "formatted": "Test Applicant",
            "givenName": "Test",
            "familyName": "Applicant"
          },
          "active": true,
          "id": "048A0501-6188-4CDE-A301-2FA840E87CC7",
          "userName": "test1@mail.com",
          "urn:ietf:params:scim:schemas:ian:2.0:User": {
            "loadToDataVaultDate": "2021-01-22 02:23:16",
            "tenantKey": "709",
            "loadToDataMartDate": "2021-01-22 06:05:06",
            "EXTERNAL_USER_ID": "00000000-0000-0000-0000-000000000002"
          },
        },
        {
          "emails": [
            {
              "type": "work",
              "value": "test2.user@mail.com",
              "primary": true
            }
          ],
          "addresses": [
            {
              "country": "United States",
              "streetAddress": "4005 Duckhorn Drive",
              "formatted": "4005 Duckhorn Drive  Coraopolis Pennsylvania United States",
              "postalCode": "15108",
              "locality": "Coraopolis",
              "region": "Pennsylvania",
              "type": "home",
              "primary": true
            }
          ],
          "meta": {
            "location": "Users/048A0502-409F-4E91-8E03-CD7E41C5F0B1",
            "resourceType": "User"
          },
          "schemas": [
            "urn:ietf:params:scim:schemas:core:2.0:User",
            "urn:ietf:params:scim:schemas:ian:2.0:User",
            "urn:ietf:params:scim:schemas:extension:enterprise:2.0:User"
          ],
          "name": {
            "middleName": "William",
            "formatted": "Mr. Patrick Jane",
            "givenName": "Patrick",
            "familyName": "Jane",
            "honoroficPrefix": "Mr."
          },
          "active": true,
          "id": "048A0502-409F-4E91-8E03-CD7E41C5F0B1",
          "userName": "test2.user@mail.com",
          "urn:ietf:params:scim:schemas:ian:2.0:User": {
            "loadToDataVaultDate": "2021-01-22 02:25:31",
            "tenantKey": "709",
            "formerLastName": "Flyak",
            "loadToDataMartDate": "2021-01-22 06:05:06"
          }
        },
        {
          "emails": [
            {
              "type": "work",
              "value": "test3.user@mail.com",
              "primary": true
            }
          ],
          "addresses": [
            {
              "country": "United States",
              "streetAddress": "1791 Calvert Farms Drive",
              "formatted": "1791 Calvert Farms Drive  Greenwood Indiana United States",
              "postalCode": "46143",
              "locality": "Greenwood",
              "region": "Indiana",
              "type": "home",
              "primary": true
            }
          ],
          "meta": {
            "location": "Users/048A0503-85BE-45BF-A2BE-0F85A21D81E0",
            "resourceType": "User"
          },
          "schemas": [
            "urn:ietf:params:scim:schemas:core:2.0:User",
            "urn:ietf:params:scim:schemas:ian:2.0:User",
            "urn:ietf:params:scim:schemas:extension:enterprise:2.0:User"
          ],
          "name": {
            "middleName": "Dan",
            "formatted": "Mr. Janice Lee",
            "givenName": "Janice",
            "familyName": "Lee",
            "honoroficPrefix": "Mr."
          },
          "active": true,
          "id": "048A0503-85BE-45BF-A2BE-0F85A21D81E0",
          "userName": "test3.user@mail.com",
          "urn:ietf:params:scim:schemas:ian:2.0:User": {
            "loadToDataVaultDate": "2021-01-22 02:24:51",
            "tenantKey": "709",
            "formerLastName": "Helton",
            "loadToDataMartDate": "2021-01-22 06:05:06"
          }
        },
        {
          "emails": [
            {
              "type": "work",
              "value": "test4.user@mail.com",
              "primary": true
            }
          ],
          "addresses": [
            {
              "country": "United States",
              "streetAddress": "566 Big Brown Dr",
              "formatted": "566 Big Brown Dr  Austin Texas United States",
              "postalCode": "78737",
              "locality": "Austin",
              "region": "Texas",
              "type": "home",
              "primary": true
            }
          ],
          "meta": {
            "location": "Users/048A0504-4B45-4B95-9076-64DFF2D9FA69",
            "resourceType": "User"
          },
          "schemas": [
            "urn:ietf:params:scim:schemas:core:2.0:User",
            "urn:ietf:params:scim:schemas:ian:2.0:User",
            "urn:ietf:params:scim:schemas:extension:enterprise:2.0:User"
          ],
          "name": {
            "formatted": "Mr. Robert Sullivan",
            "givenName": "Robert",
            "familyName": "Sullivan",
            "honoroficPrefix": "Mr."
          },
          "active": true,
          "id": "048A0504-4B45-4B95-9076-64DFF2D9FA69",
          "userName": "test4.user@mail.com",
          "urn:ietf:params:scim:schemas:ian:2.0:User": {
            "county": "Hayes",
            "loadToDataVaultDate": "2021-01-22 02:27:02",
            "tenantKey": "709",
            "loadToDataMartDate": "2021-01-22 06:05:06"
          }
        },
        {
          "emails": [
            {
              "type": "work",
              "value": "test5.user@mail.com",
              "primary": true
            }
          ],
          "addresses": [
            {
              "country": "United States",
              "streetAddress": "13808 Colin St",
              "formatted": "13808 Colin St  Frisco Texas United States",
              "postalCode": "75035",
              "locality": "Frisco",
              "region": "Texas",
              "type": "home",
              "primary": true
            }
          ],
          "meta": {
            "location": "Users/048A0505-71DE-4BB1-ABBD-32125AEAA1C4",
            "resourceType": "User"
          },
          "schemas": [
            "urn:ietf:params:scim:schemas:core:2.0:User",
            "urn:ietf:params:scim:schemas:ian:2.0:User",
            "urn:ietf:params:scim:schemas:extension:enterprise:2.0:User"
          ],
          "name": {
            "middleName": "Van",
            "formatted": "Miss. Grace Van Pelt",
            "givenName": "Garce",
            "familyName": "Pelt",
            "honoroficPrefix": "Miss."
          },
          "active": true,
          "id": "048A0505-71DE-4BB1-ABBD-32125AEAA1C4",
          "userName": "test5.user@mail.com",
          "urn:ietf:params:scim:schemas:ian:2.0:User": {
            "county": "Collin",
            "loadToDataVaultDate": "2021-01-22 02:25:46",
            "tenantKey": "709",
            "formerLastName": "Roth",
            "loadToDataMartDate": "2021-01-22 06:05:06"
          }
        },
        {
          "emails": [
            {
              "type": "work",
              "value": "test6.user@mail.com",
              "primary": true
            }
          ],
          "addresses": [
            {
              "country": "United States",
              "streetAddress": "71 Chaucer Dr",
              "formatted": "71 Chaucer Dr  Pleasant Hill California United States",
              "postalCode": "94523",
              "locality": "Pleasant Hill",
              "region": "California",
              "type": "home",
              "primary": true
            }
          ],
          "meta": {
            "location": "Users/048A0506-71E0-434E-BB37-DDDAE659E160",
            "resourceType": "User"
          },
          "schemas": [
            "urn:ietf:params:scim:schemas:core:2.0:User",
            "urn:ietf:params:scim:schemas:ian:2.0:User",
            "urn:ietf:params:scim:schemas:extension:enterprise:2.0:User"
          ],
          "name": {
            "middleName": "Joseph",
            "formatted": "Tolmino Joseph Serafini",
            "givenName": "Tolmino",
            "familyName": "Serafini"
          },
          "active": true,
          "id": "048A0506-71E0-434E-BB37-DDDAE659E160",
          "userName": "tjserafini@gmail.com",
          "urn:ietf:params:scim:schemas:ian:2.0:User": {
            "loadToDataVaultDate": "2021-01-22 02:22:43",
            "tenantKey": "709",
            "loadToDataMartDate": "2021-01-22 06:05:06",
            "EXTERNAL_USER_ID": "048A1501-14C9-4881-8829-12EA81508AC4"
          },
          "phoneNumbers": [
            {
              "type": "work",
              "value": "650-576-5010",
              "primary": true
            }
          ]
        },
        {
          "emails": [
            {
              "type": "work",
              "value": "test7.user@mail.com",
              "primary": true
            }
          ],
          "addresses": [
            {
              "country": "United States",
              "streetAddress": "2504 Naperton Drive",
              "formatted": "2504 Naperton Drive  Plano Texas United States",
              "postalCode": "75025",
              "locality": "Plano",
              "region": "Texas",
              "type": "home",
              "primary": true
            }
          ],
          "meta": {
            "location": "Users/048A0507-F3EF-41FA-9986-C350F8022FF1",
            "resourceType": "User"
          },
          "schemas": [
            "urn:ietf:params:scim:schemas:core:2.0:User",
            "urn:ietf:params:scim:schemas:ian:2.0:User",
            "urn:ietf:params:scim:schemas:extension:enterprise:2.0:User"
          ],
          "name": {
            "formatted": "Mrs. Carol Danvers",
            "givenName": "Carol",
            "familyName": "Danvers",
            "honoroficPrefix": "Mrs."
          },
          "active": true,
          "id": "048A0507-F3EF-41FA-9986-C350F8022FF1",
          "userName": "test7.user@mail.com",
          "urn:ietf:params:scim:schemas:ian:2.0:User": {
            "loadToDataVaultDate": "2021-01-22 02:25:37",
            "tenantKey": "709",
            "loadToDataMartDate": "2021-01-22 06:05:06",
            "EXTERNAL_USER_ID": "048A1502-6B02-4B0B-B897-7DDA03B1E0F0"
          }
        },
        {
          "emails": [
            {
              "type": "work",
              "value": "test8.user@mail.com",
              "primary": true
            }
          ],
          "addresses": [
            {
              "country": "United States",
              "streetAddress": "6080 Water Street Apt 1337",
              "formatted": "6080 Water Street Apt 1337 Plano Texas United States",
              "postalCode": "75024",
              "locality": "Plano",
              "region": "Texas",
              "type": "home",
              "primary": true
            }
          ],
          "meta": {
            "location": "Users/048A0508-89F5-41B3-9241-4B32373FE217",
            "resourceType": "User"
          },
          "schemas": [
            "urn:ietf:params:scim:schemas:core:2.0:User",
            "urn:ietf:params:scim:schemas:ian:2.0:User",
            "urn:ietf:params:scim:schemas:extension:enterprise:2.0:User"
          ],
          "name": {
            "formatted": "Mr. Kimbal Cho",
            "givenName": "Kimbal",
            "familyName": "Cho",
            "honoroficPrefix": "Mr."
          },
          "active": true,
          "id": "048A0508-89F5-41B3-9241-4B32373FE217",
          "userName": "test8.user@yahoo.com",
          "urn:ietf:params:scim:schemas:ian:2.0:User": {
            "loadToDataVaultDate": "2021-01-22 02:27:07",
            "tenantKey": "709",
            "loadToDataMartDate": "2021-01-22 06:05:06",
            "EXTERNAL_USER_ID": "048A1503-83E8-4C7F-8BF4-AB0C72412433"
          }
        },
        {
          "emails": [
            {
              "type": "work",
              "value": "test9.user@mail.com",
              "primary": true
            }
          ],
          "addresses": [
            {
              "country": "United States",
              "streetAddress": "7520 Gibraltar St Unit C",
              "formatted": "7520 Gibraltar St Unit C Carlsbad California United States",
              "postalCode": "92009",
              "locality": "Carlsbad",
              "region": "California",
              "type": "home",
              "primary": true
            }
          ],
          "meta": {
            "location": "Users/048A0509-0D08-44AC-99C0-24B088C27D76",
            "resourceType": "User"
          },
          "schemas": [
            "urn:ietf:params:scim:schemas:core:2.0:User",
            "urn:ietf:params:scim:schemas:ian:2.0:User",
            "urn:ietf:params:scim:schemas:extension:enterprise:2.0:User"
          ],
          "name": {
            "formatted": "Miss. Teresa Lisbon",
            "givenName": "Teresa",
            "familyName": "Lisbon",
            "honoroficPrefix": "Miss."
          },
          "active": true,
          "id": "048A0509-0D08-44AC-99C0-24B088C27D76",
          "userName": "test9.user@mail.com",
          "urn:ietf:params:scim:schemas:ian:2.0:User": {
            "county": "San Diego",
            "loadToDataVaultDate": "2021-01-22 02:25:48",
            "tenantKey": "709",
            "loadToDataMartDate": "2021-01-22 06:05:06",
            "EXTERNAL_USER_ID": "048A1504-BD70-4D58-99E5-40953659DCE0"
          },
          "phoneNumbers": [
            {
              "type": "work",
              "value": "+1 615-481-9999",
              "primary": true
            }
          ]
        }
      ],
      "itemsPerPage": 10,
      "schemas": [
        "urn:ietf:params:scim:api:messages:2.0:ListResponse"
      ]
    }